{
    "key": "group_roadmap_stepper_block",
    "title": "Roadmap Stepper Block",
    "fields": [
        {
            "key": "field_roadmap_title",
            "label": "Block Title",
            "name": "block_title",
            "aria-label": "",
            "type": "text",
            "instructions": "",
            "required": false,
            "conditional_logic": false,
            "wrapper": {
                "width": "",
                "class": "",
                "id": ""
            },
            "default_value": "Our DevOps Strategy Roadmap",
            "maxlength": "",
            "placeholder": "",
            "prepend": "",
            "append": ""
        },
        {
            "key": "field_roadmap_image",
            "label": "Right Side Image",
            "name": "right_image",
            "aria-label": "",
            "type": "image",
            "instructions": "",
            "required": false,
            "conditional_logic": false,
            "wrapper": {
                "width": "",
                "class": "",
                "id": ""
            },
            "return_format": "array",
            "preview_size": "medium",
            "library": "all",
            "min_width": 0,
            "min_height": 0,
            "min_size": 0,
            "max_width": 0,
            "max_height": 0,
            "max_size": 0,
            "mime_types": ""
        },
        {
            "key": "field_roadmap_steps",
            "label": "Roadmap Steps",
            "name": "roadmap_steps",
            "aria-label": "",
            "type": "repeater",
            "instructions": "",
            "required": false,
            "conditional_logic": false,
            "wrapper": {
                "width": "",
                "class": "",
                "id": ""
            },
            "layout": "table",
            "button_label": "Add Step",
            "min": 0,
            "max": 0,
            "rows_per_page": 20,
            "collapsed": "",
            "sub_fields": [
                {
                    "key": "field_step_icon",
                    "label": "Step Icon",
                    "name": "step_icon",
                    "aria-label": "",
                    "type": "select",
                    "instructions": "",
                    "required": false,
                    "conditional_logic": false,
                    "wrapper": {
                        "width": "",
                        "class": "",
                        "id": ""
                    },
                    "choices": {
                        "chart": "Chart\/Analytics",
                        "cog": "Settings\/Automation",
                        "clipboard": "Document\/Build",
                        "infinity": "Infinity\/Optimize",
                        "users": "Users\/Team",
                        "rocket": "Rocket\/Launch",
                        "shield": "Shield\/Security",
                        "target": "Target\/Goals"
                    },
                    "default_value": "chart",
                    "multiple": 0,
                    "allow_null": 0,
                    "ui": 0,
                    "ajax": 0,
                    "placeholder": "",
                    "return_format": "value",
                    "create_options": 0,
                    "save_options": 0,
                    "parent_repeater": "field_roadmap_steps"
                },
                {
                    "key": "field_step_title",
                    "label": "Step Title",
                    "name": "step_title",
                    "aria-label": "",
                    "type": "text",
                    "instructions": "",
                    "required": 1,
                    "conditional_logic": false,
                    "wrapper": {
                        "width": "",
                        "class": "",
                        "id": ""
                    },
                    "default_value": "",
                    "maxlength": "",
                    "placeholder": "",
                    "prepend": "",
                    "append": "",
                    "parent_repeater": "field_roadmap_steps"
                },
                {
                    "key": "field_step_description",
                    "label": "Step Description",
                    "name": "step_description",
                    "aria-label": "",
                    "type": "textarea",
                    "instructions": "",
                    "required": false,
                    "conditional_logic": false,
                    "wrapper": {
                        "width": "",
                        "class": "",
                        "id": ""
                    },
                    "rows": 3,
                    "default_value": "",
                    "new_lines": "",
                    "maxlength": "",
                    "placeholder": "",
                    "parent_repeater": "field_roadmap_steps"
                }
            ]
        }
    ],
    "location": [
        [
            {
                "param": "block",
                "operator": "==",
                "value": "acf\/roadmap-stepper"
            }
        ]
    ],
    "menu_order": 0,
    "position": "normal",
    "style": "default",
    "label_placement": "top",
    "instruction_placement": "label",
    "hide_on_screen": [],
    "active": true,
    "description": "",
    "show_in_rest": false,
    "display_title": "",
    "modified": 1766392800
}
